LICENSE
README.md
setup.py
SACalendar/Calendar.py
SACalendar/__init__.py
SACalendar/exceptions.py
SACalendar.egg-info/PKG-INFO
SACalendar.egg-info/SOURCES.txt
SACalendar.egg-info/dependency_links.txt
SACalendar.egg-info/requires.txt
SACalendar.egg-info/top_level.txt