Metadata-Version: 2.1
Name: SACalendar
Version: 0.0.2
Summary: Simple calendar for telegram bot (aiogram v2.x)
Home-page: https://github.com/bbt-t/SACalendar
Author: Nik Bbt-t
Author-email: bbt-pip@yandex.ru
License: MIT License
Download-URL: https://github.com/bbt-t/SACalendar/archive/refs/tags/v0.0.2.tar.gz
Keywords: async,aiogram,telegram,bot,calendar
Platform: UNKNOWN
Classifier: Programming Language :: Python :: 3.10
License-File: LICENSE
